{
    "description": "You are an infrastructure engineer writing a quick smoke-test for a local\n    \u201cmock API\u201d file that will later be served over HTTP.  \n    Everything you need already exists inside the home directory; **do not try to\n    access the public Internet.**\n\n    Goal  \n    -----  \n    1. Issue a single, one-liner *curl* command that:  \n       \u2022 Reads the file located at\n         file:///home/user/mock_api/users.json  \n       \u2022 Saves the body exactly as it is to\n         /home/user/provision_output/users_response.json  \n       \u2022 Writes a tiny log line to\n         /home/user/provision_logs/api_test.log that contains only:  \n\n         STATUS=SUCCESS|||SIZE=&lt;bytes&gt;\n\n         where &lt;bytes&gt; is the number of bytes *curl* actually downloaded.  \n    2. The command must be self-contained: you may chain sub-commands with \u201c&&\u201d,\n       but everything must be entered on **one** terminal line.  \n    3. The required directory structure must exist when the command finishes:\n       /home/user/provision_output/ and /home/user/provision_logs/.\n\n    Exact output formats the grader will verify  \n    -------------------------------------------  \n    \u2022 /home/user/provision_output/users_response.json **must contain exactly**  \n      {\"users\":[{\"id\":1,\"name\":\"Alice\"},{\"id\":2,\"name\":\"Bob\"}]}  \n\n      (no trailing newline).  \n\n    \u2022 /home/user/provision_logs/api_test.log **must consist of one line** that\n      ends with a newline character \u201c\\n\u201d and matches exactly:  \n\n      STATUS=SUCCESS|||SIZE=57\\n\n\n      \u2013 \u201cSTATUS=SUCCESS\u201d (all caps, no spaces)  \n      \u2013 the literal triple-bar separator \u201c|||\u201d  \n      \u2013 \u201cSIZE=\u201d followed by the byte count reported by *curl -w %{size_download}*\n        (for the given file it must be 57).  \n      \u2013 A single LF newline at the very end.\n\n    Success criteria  \n    ----------------  \n    The automated grader will:  \n    1. Check that both required directories exist.  \n    2. Verify that /home/user/provision_output/users_response.json is present and\n       its contents are **bit-for-bit** identical to the string above.  \n    3. Verify that /home/user/provision_logs/api_test.log exists and contains the\n       exact string \u201cSTATUS=SUCCESS|||SIZE=57\\n\u201d.\n\n    Hints (do not print these)  \n    --------------------------  \n    \u2022 The *curl* \u201cfile://\u201d protocol works on regular files.  \n    \u2022 \u201c-o\u201d saves the body, \u201c-s\u201d silences progress, \u201c-w\u201d can emit a custom string\n      containing \u201c%{size_download}\u201d.  \n    \u2022 Use \u201cmkdir -p\u201d to build directory trees and \u201c&&\u201d to keep it all in one\n      command line.",
    "truth": "Initial state supplied to the agent\n    ----------------------------------\n    1. Directory: /home/user/mock_api/\n    2. File: /home/user/mock_api/users.json\n       Exact contents (57 bytes, no newline):\n       {\"users\":[{\"id\":1,\"name\":\"Alice\"},{\"id\":2,\"name\":\"Bob\"}]}\n\n    Expected artifacts after successful completion\n    ----------------------------------------------\n    1. Directory: /home/user/provision_output/      (must exist)\n    2. Directory: /home/user/provision_logs/        (must exist)\n\n    3. File: /home/user/provision_output/users_response.json\n       Exact contents (identical copy of the source file):\n       {\"users\":[{\"id\":1,\"name\":\"Alice\"},{\"id\":2,\"name\":\"Bob\"}]}\n\n    4. File: /home/user/provision_logs/api_test.log\n       Exact contents (including trailing LF):\n       STATUS=SUCCESS|||SIZE=57\\n",
    "name": "task_000000_0ec4b6cb"
}